bagpipe/__init__.py
bagpipe/preprocessing.py
bagpipe_python-0.0.7.dist-info/METADATA
bagpipe_python-0.0.7.dist-info/WHEEL
bagpipe_python-0.0.7.dist-info/licenses/LICENSE
bagpipe_python-0.0.7.dist-info/RECORD
