Metadata-Version: 2.1
Name: bagpipe-python
Version: 0.0.7
Summary: Bagpipe is a scikit-learn powered preprocessing library for listed dataframes based on the pipline structure of sklearn.
Author-email: Noah Puetz <noah_christoph.puetz@th-koeln.de>, Jens Brandt <jens_uwe.brandt@th-koeln.de>
License-File: LICENSE
Classifier: License :: OSI Approved :: MIT License
Classifier: Operating System :: OS Independent
Classifier: Programming Language :: Python :: 3
Requires-Python: >=3.10
